[
    {
    "tipo":"Hand Roll",
    "nombre": "Teriyaki Roll",
    "ingredientes":["Pollo teriyaki", "Queso crema", "Cebollín"],
    "precio": 2500,
    "imagenURL":"https://tofuu.getjusto.com/orioneat-prod/fjzscSzZyeC5FWPvg-56%20mix.jpeg"
    },
    {
    "tipo":"Hand Roll",
    "nombre": "Kani Roll",
    "ingredientes":["Kanikama", "Queso crema", "Cebollín"],
    "precio": 2500,
    "imagenURL":"https://tofuu.getjusto.com/orioneat-prod/fjzscSzZyeC5FWPvg-56%20mix.jpeg"
    },
    {
    "tipo":"Hand Roll",
    "nombre": "Tori Roll",
    "ingredientes":["Pollo Apanado", "Palta", "Queso crema", "Cebollín"],
    "precio": 3000,
    "imagenURL":"https://tofuu.getjusto.com/orioneat-prod/fjzscSzZyeC5FWPvg-56%20mix.jpeg"
    },
    {
    "tipo":"Hand Roll",
    "nombre": "Ebi Furay",
    "ingredientes":["Salmon Apanado/Natural", "Queso crema", "Cebollín"],
    "precio": 3500,
    "imagenURL":"https://tofuu.getjusto.com/orioneat-prod/fjzscSzZyeC5FWPvg-56%20mix.jpeg"
    },
    {
    "tipo":"Hand Roll",
    "nombre": "Tako Roll",
    "ingredientes":["Pulpo", "Palta", "Queso crema", "Cebollín"],
    "precio": 4000,
    "imagenURL":"https://tofuu.getjusto.com/orioneat-prod/fjzscSzZyeC5FWPvg-56%20mix.jpeg"
    },
    {
    "tipo":"California Rolls",
    "nombre": "Tori Roll",
    "ingredientes":["Pollo Apanado", "Queso crema", "Cebollín"],
    "precio": 3100,
    "imagenURL":"https://tofuu.getjusto.com/orioneat-prod/fjzscSzZyeC5FWPvg-56%20mix.jpeg"
    },
    {
    "tipo":"California Rolls",
    "nombre": "Avocado Roll",
    "ingredientes":["Palta", "Queso crema", "Cebollín"],
    "precio": 2800,
    "imagenURL":"https://tofuu.getjusto.com/orioneat-prod/fjzscSzZyeC5FWPvg-56%20mix.jpeg"
    },
    {
    "tipo":"California Rolls",
    "nombre": "Champi Roll",
    "ingredientes":["Champiñon Salteado", "Queso crema", "Cebollín"],
    "precio": 3000,
    "imagenURL":"https://tofuu.getjusto.com/orioneat-prod/fjzscSzZyeC5FWPvg-56%20mix.jpeg"
    },
    {
    "tipo":"California Rolls",
    "nombre": "Light Roll",
    "ingredientes":["Palmito", "Palta", "Queso crema", "Cebollín"],
    "precio": 3000,
    "imagenURL":"https://tofuu.getjusto.com/orioneat-prod/fjzscSzZyeC5FWPvg-56%20mix.jpeg"
    },
    {
    "tipo":"California Rolls",
    "nombre": "Tori Chili",
    "ingredientes":["Pollo Apanado", "Merken", "Queso crema", "Cebollín"],
    "precio": 3300,
    "imagenURL":"https://tofuu.getjusto.com/orioneat-prod/fjzscSzZyeC5FWPvg-56%20mix.jpeg"
    },
    {
    "tipo":"Cream Cheese Rolls",
    "nombre": "Crunch Light",
    "ingredientes":["Palta", "Choclo", "Bañado almendra/nuez"],
    "precio": 3600,
    "imagenURL":"https://tofuu.getjusto.com/orioneat-prod/fjzscSzZyeC5FWPvg-56%20mix.jpeg"
    },
    {
    "tipo":"Cream Cheese Rolls",
    "nombre": "Ebi Furay",
    "ingredientes":["Camaron Apanado", "Queso crema", "Cebollín"],
    "precio": 4100,
    "imagenURL":"https://tofuu.getjusto.com/orioneat-prod/fjzscSzZyeC5FWPvg-56%20mix.jpeg"
    },
    {
    "tipo":"Cream Cheese Rolls",
    "nombre": "Tori Avocado",
    "ingredientes":["Pollo Apanado", "Queso crema", "Cebollín"],
    "precio": 4100,
    "imagenURL":"https://tofuu.getjusto.com/orioneat-prod/fjzscSzZyeC5FWPvg-56%20mix.jpeg"
    },
    {
    "tipo":"Cream Cheese Rolls",
    "nombre": "Teriyaki Avocado",
    "ingredientes":["Pollo teriyaki", "Palta", "Queso crema", "Cebollín"],
    "precio": 4100,
    "imagenURL":"https://tofuu.getjusto.com/orioneat-prod/fjzscSzZyeC5FWPvg-56%20mix.jpeg"
    },
    {
    "tipo":"Cream Cheese Rolls",
    "nombre": "Kani Roll",
    "ingredientes":["Kanikama", "Queso crema", "Cebollín"],
    "precio": 3400,
    "imagenURL":"https://tofuu.getjusto.com/orioneat-prod/fjzscSzZyeC5FWPvg-56%20mix.jpeg"
    },
    {
    "tipo":"Sake Rolls",
    "nombre": "Tori Roll",
    "ingredientes":["Pollo Apanado", "Queso crema", "Cebollín"],
    "precio": 4490,
    "imagenURL":"https://tofuu.getjusto.com/orioneat-prod/fjzscSzZyeC5FWPvg-56%20mix.jpeg"
    },
    {
    "tipo":"Sake Rolls",
    "nombre": "Tako Roll",
    "ingredientes":["Pulpo", "Palta", "Queso crema", "Cebollín"],
    "precio": 4990,
    "imagenURL":"https://tofuu.getjusto.com/orioneat-prod/fjzscSzZyeC5FWPvg-56%20mix.jpeg"
    },
    {
    "tipo":"Sake Rolls",
    "nombre": "Sake Roll",
    "ingredientes":["Salmon", "Queso crema", "Cebollín"],
    "precio": 4990,
    "imagenURL":"https://tofuu.getjusto.com/orioneat-prod/fjzscSzZyeC5FWPvg-56%20mix.jpeg"
    },
    {
    "tipo":"Sake Rolls",
    "nombre": "Ebi Roll",
    "ingredientes":["Camaron", "Queso crema", "Cebollín"],
    "precio": 4690,
    "imagenURL":"https://tofuu.getjusto.com/orioneat-prod/fjzscSzZyeC5FWPvg-56%20mix.jpeg"
    },
    {
    "tipo":"Sake Rolls",
    "nombre": "Sake Tako Roll",
    "ingredientes":["Salmon", "Pulpo", "Queso crema", "Cebollín"],
    "precio": 5990,
    "imagenURL":"https://tofuu.getjusto.com/orioneat-prod/fjzscSzZyeC5FWPvg-56%20mix.jpeg"
    },
    {
    "tipo":"Tempura Rolls",
    "nombre": "Kani Roll",
    "ingredientes":["Kanikama", "Queso crema", "Cebollín"],
    "precio": 3000,
    "imagenURL":"https://tofuu.getjusto.com/orioneat-prod/fjzscSzZyeC5FWPvg-56%20mix.jpeg"
    },
    {
    "tipo":"Tempura Rolls",
    "nombre": "Champi Roll",
    "ingredientes":["Champiñon Salteado", "Queso crema", "Cebollín"],
    "precio": 3190,
    "imagenURL":"https://tofuu.getjusto.com/orioneat-prod/fjzscSzZyeC5FWPvg-56%20mix.jpeg"
    },
    {
    "tipo":"Tempura Rolls",
    "nombre": "Tori Avocado",
    "ingredientes":["Pollo Apanado", "Queso crema", "Cebollín"],
    "precio": 3190,
    "imagenURL":"https://tofuu.getjusto.com/orioneat-prod/fjzscSzZyeC5FWPvg-56%20mix.jpeg"
    },
    {
    "tipo":"Tempura Rolls",
    "nombre": "Sake Roll",
    "ingredientes":["Salmon", "Queso crema", "Cebollín"],
    "precio": 3800,
    "imagenURL":"https://tofuu.getjusto.com/orioneat-prod/fjzscSzZyeC5FWPvg-56%20mix.jpeg"
    },
    {
    "tipo":"Tempura Rolls",
    "nombre": "Ebi Avocado",
    "ingredientes":["Camaron", "Palta", "Queso crema", "Cebollín"],
    "precio": 3890,
    "imagenURL":"https://tofuu.getjusto.com/orioneat-prod/fjzscSzZyeC5FWPvg-56%20mix.jpeg"
    },
    {
    "tipo":"Rolls sin arroz",
    "nombre": "Light Roll",
    "ingredientes": ["Palmito", "Choclo", "Palta", "Queso crema"],
    "precio": 4990,
    "imagenURL":"https://tofuu.getjusto.com/orioneat-prod/fjzscSzZyeC5FWPvg-56%20mix.jpeg"
    },
    {
    "tipo":"Rolls sin arroz",
    "nombre": "Champi Avocado",
    "ingredientes":["Champiñon Salteado", "Palta", "Queso crema", "Cebollín"],
    "precio": 5290,
    "imagenURL":"https://tofuu.getjusto.com/orioneat-prod/fjzscSzZyeC5FWPvg-56%20mix.jpeg"
    },
    {
    "tipo":"Rolls sin arroz",
    "nombre": "Sake Avocado",
    "ingredientes":["Salmon", "Palta", "Queso crema", "Cebollín"],
    "precio": 6290,
    "imagenURL":"https://tofuu.getjusto.com/orioneat-prod/fjzscSzZyeC5FWPvg-56%20mix.jpeg"
    },
    {
    "tipo":"Rolls sin arroz",
    "nombre": "Umi Roll",
    "ingredientes":["Camaron", "Salmon" , "Queso crema", "Cebollín"],
    "precio": 6690,
    "imagenURL":"https://tofuu.getjusto.com/orioneat-prod/fjzscSzZyeC5FWPvg-56%20mix.jpeg"
    },
    {
    "tipo":"Rolls sin arroz",
    "nombre": "Umi Furay Roll",
    "ingredientes":["Camaron Apanado", "Salmon Apanado", "Queso crema"],
    "precio": 6990,
    "imagenURL":"https://tofuu.getjusto.com/orioneat-prod/fjzscSzZyeC5FWPvg-56%20mix.jpeg"
    },
]